slurm_jupyter/__init__.py
slurm_jupyter/templates.py
slurm_jupyter/testing.py
slurm_jupyter/utils.py
slurm_jupyter-2.5.11.data/scripts/config-slurm-jupyter.sh
slurm_jupyter-2.5.11.dist-info/LICENSE
slurm_jupyter-2.5.11.dist-info/METADATA
slurm_jupyter-2.5.11.dist-info/WHEEL
slurm_jupyter-2.5.11.dist-info/entry_points.txt
slurm_jupyter-2.5.11.dist-info/top_level.txt
slurm_jupyter-2.5.11.dist-info/RECORD
