Metadata-Version: 2.1
Name: slurm-jupyter
Version: 2.5.11
Summary: Utilities for jupyter on a slurm cluster.
Home-page: https://github.com/kaspermunch/slurm-jupyter
Author: Kasper Munch
Author-email: kaspermunch@birc.au.dk
Classifier: Programming Language :: Python :: 3
Classifier: License :: OSI Approved :: MIT License
Classifier: Operating System :: OS Independent
Requires-Python: >=3.6
License-File: LICENSE
Requires-Dist: colorama >=0.4
Requires-Dist: packaging >=21.0
